{"cameraMode":{"drawMode":0,"name":"Shaded","section":"Shading Mode"},"sceneLighting":true,"audioPlay":false,"sceneViewState":{"m_AlwaysRefresh":false,"showFog":true,"showSkybox":true,"showFlares":true,"showImageEffects":true,"showParticleSystems":true,"showVisualEffectGraphs":true,"m_FxEnabled":true},"in2DMode":false,"pivot":{"x":89.7715835571289,"y":58.347076416015628,"z":33.8883056640625},"rotation":{"x":-0.007144107483327389,"y":0.525904655456543,"z":0.0044181556440889839,"w":0.8505063056945801},"size":12.12435531616211,"orthographic":false}