{"cameraMode":{"drawMode":0,"name":"Shaded","section":"Shading Mode"},"sceneLighting":true,"audioPlay":false,"sceneViewState":{"m_AlwaysRefresh":false,"showFog":true,"showSkybox":true,"showFlares":true,"showImageEffects":true,"showParticleSystems":true,"showVisualEffectGraphs":true,"m_FxEnabled":true},"in2DMode":false,"pivot":{"x":139.531005859375,"y":7.308447360992432,"z":203.14112854003907},"rotation":{"x":0.20581021904945374,"y":0.39250698685646059,"z":-0.0905793309211731,"w":0.8918402194976807},"size":75.6394271850586,"orthographic":false}